cognite/edm/__init__.py
cognite/edm/connector/__init__.py
cognite/edm/connector/native/__init__.py
cognite/edm/connector/native/edm_native_v1_pb2.py
cognite/edm/connector/native/edm_native_v1_pb2.pyi
cognite_edm_data-2.0.1.dist-info/METADATA
cognite_edm_data-2.0.1.dist-info/WHEEL
cognite_edm_data-2.0.1.dist-info/top_level.txt
cognite_edm_data-2.0.1.dist-info/RECORD
