Metadata-Version: 2.1
Name: cognite-edm-data
Version: 2.0.1
Summary: Python package to decode/encode data objects related to the Cognite EDM Connector
Home-page: https://github.com/cognitedata/edm-connector-protobuf
Author: Thorkild Stray
Author-email: thorkild.stray@cognite.com
License: UNKNOWN
Platform: UNKNOWN
Requires-Python: >=3.5
Requires-Dist: setuptools
Requires-Dist: protobuf>=4.0.0
